numalg/__init__.py
numalg/bisseccao.py
numalg/bvp.py
numalg/bvp2.py
numalg/compgauss2nodes.py
numalg/compgauss3nodes.py
numalg/cspline.py
numalg/errorteor.py
numalg/euler.py
numalg/eulerrn.py
numalg/gaussSeidel.py
numalg/heun.py
numalg/heunrn.py
numalg/jacobi.py
numalg/lagrangepol.py
numalg/midpoint.py
numalg/midpointedo.py
numalg/midpointedorn.py
numalg/mmq.py
numalg/newtonGen.py
numalg/newton_raphson.py
numalg/polinomioNewton.py
numalg/polynewton.py
numalg/polyvalLagrange.py
numalg/pontofixo.py
numalg/rungekutta4.py
numalg/rungekutta4rn.py
numalg/secante.py
numalg/simpson.py
numalg/simpsonmetodo.py
numalg/sorgs.py
numalg/splinelinear.py
numalg/taylor2.py
numalg/taylor2rn.py
numalg/trapezios.py
numalg/trapz.py
numalg-1.0.6.dist-info/licenses/LICENSE
numalg-1.0.6.dist-info/METADATA
numalg-1.0.6.dist-info/WHEEL
numalg-1.0.6.dist-info/top_level.txt
numalg-1.0.6.dist-info/RECORD
