Metadata-Version: 2.4
Name: numalg
Version: 1.0.6
Summary: Numerical analysis algorithms
Home-page: https://github.com/isabel-mc/pip
Author: Isabel Reis dos Santos
Author-email: isabel.santos@tecnico.ulisboa.pt
License: MIT
Classifier: Programming Language :: Python :: 3
Classifier: Operating System :: OS Independent
Classifier: Intended Audience :: Developers
Classifier: Topic :: Scientific/Engineering :: Mathematics
Classifier: Development Status :: 4 - Beta
Classifier: Environment :: Console
Requires-Python: >=3.6
License-File: LICENSE
Requires-Dist: numpy
Dynamic: author
Dynamic: author-email
Dynamic: classifier
Dynamic: description
Dynamic: description-content-type
Dynamic: home-page
Dynamic: license
Dynamic: license-file
Dynamic: requires-dist
Dynamic: requires-python
Dynamic: summary
